{
  "name": "Classic 0.30 Creative",
  "md5": "A093FA158DC9D1FA7EC6128C5D77B8A5",
  "sha256": "7B0E89C5F8F75374A154DCA356D14563DA6388B33D8F4687946DA2B0CB219A70",
  "type": "client",
  "enableScreenshotPatch": true,
  "enableFullscreenPatch": true,
  "enableCursorPatch": true,
  "legacy": true,
  "baseVersion": "c0.30-c",
  "guiClass": "com.mojang.minecraft.e.m",
  "guiScreenClass": "com.mojang.minecraft.e.o",
  "useFOVPatch": true,
  "useTexturepackPatch": true,
  "ingameVersionString": "0.30",
  "resourcesVersion": "a1.0.1_01",
  "optionsVersion": "CLASSIC"
}
